cli_enterprise/__init__.py
cli_enterprise/entcli/__init__.py
cli_enterprise/entcli/cli.py
cli_enterprise/entcli/configutils.py
cli_enterprise/entcli/fileutils.py
cli_enterprise/entcli/httputils.py
cli_enterprise/entcli/jsonutils.py
prancer_cli-1.0.9.dist-info/METADATA
prancer_cli-1.0.9.dist-info/WHEEL
prancer_cli-1.0.9.dist-info/entry_points.txt
prancer_cli-1.0.9.dist-info/top_level.txt
prancer_cli-1.0.9.dist-info/RECORD
