Metadata-Version: 2.1
Name: prancer-cli
Version: 1.0.9
Summary: Prancer CLI, http://prancer.io/
Home-page: https://ebizframework.visualstudio.com/whitekite
Author: Farshid M/Ajey Khanapuri
Author-email: ajey.khanapuri@liquware.com
License: Propietary
Platform: UNKNOWN
Classifier: Development Status :: 3 - Alpha
Classifier: Topic :: Software Development :: Libraries :: Application Frameworks
Classifier: Topic :: Software Development :: Libraries :: Python Modules
Classifier: License :: OSI Approved :: BSD License
Requires-Python: >=3.0
Requires-Dist: requests (==2.24.0)
